ortega_2022/.DS_Store
ortega_2022/STPoint.py
ortega_2022/__init__.py
ortega_2022/ellipses.py
ortega_2022/ortega.py
ortega_2022/requirements.txt
ortega_2022-0.0.12.dist-info/METADATA
ortega_2022-0.0.12.dist-info/WHEEL
ortega_2022-0.0.12.dist-info/licenses/LICENSE
ortega_2022-0.0.12.dist-info/RECORD
