Metadata-Version: 2.1
Name: ortega_2022
Version: 0.0.12
Summary: A package for interaction analysis between moving individuals
Author-email: Rongxiang Su <rongxiangsu@ucsb.edu>
License-File: LICENSE
Classifier: License :: OSI Approved :: MIT License
Classifier: Operating System :: OS Independent
Classifier: Programming Language :: Python :: 3.8
Requires-Python: >=3.8
Requires-Dist: attrs
Requires-Dist: matplotlib
Requires-Dist: numpy
Requires-Dist: pandas
Requires-Dist: shapely
